src/__init__.py
src/cli.py
src/config.py
src/main.py
src/middleware.py
src/utils.py
src/servers/__init__.py
src/servers/account.py
src/servers/assets.py
src/servers/market_data.py
src/servers/order.py
src/servers/utils.py
src/tradeapi/__init__.py
src/tradeapi/base.py
src/tradeapi/finam_client.py
src/tradeapi/models.py
src/tradeapi/order/__init__.py
src/tradeapi/order/models.py
src/tradeapi/order/orders.py
finam_mcp_server-0.1.6.dist-info/METADATA
finam_mcp_server-0.1.6.dist-info/WHEEL
finam_mcp_server-0.1.6.dist-info/entry_points.txt
finam_mcp_server-0.1.6.dist-info/licenses/LICENSE
finam_mcp_server-0.1.6.dist-info/RECORD
