Metadata-Version: 2.4
Name: finam-mcp-server
Version: 0.1.6
Summary: Finam Trade API integration for Model Context Protocol (MCP)
Project-URL: Homepage, https://tradeapi.finam.ru/
Project-URL: Documentation, https://github.com/Alexander-Panov/finam-mcp#readme
Project-URL: Repository, https://github.com/Alexander-Panov/finam-mcp
Project-URL: Issues, https://github.com/Alexander-Panov/finam-mcp/issues
Project-URL: Changelog, https://github.com/Alexander-Panov/finam-mcp/releases
Author-email: Alexander Panov <palehou@gmail.com>
Maintainer-email: Alexander Panov <palehou@gmail.com>
License: MIT
License-File: LICENSE
Keywords: api,finam,finam-trade-api,market_data,mcp,model-context-protocol,trading
Classifier: Development Status :: 3 - Alpha
Classifier: Intended Audience :: Developers
Classifier: License :: OSI Approved :: MIT License
Classifier: Programming Language :: Python :: 3
Classifier: Programming Language :: Python :: 3.12
Classifier: Topic :: Office/Business :: Financial :: Investment
Classifier: Topic :: Scientific/Engineering :: Artificial Intelligence
Classifier: Topic :: Software Development :: Libraries :: Python Modules
Requires-Python: >=3.12
Requires-Dist: click>=8.3.1
Requires-Dist: fastmcp>=2.13.3
Requires-Dist: finam-trade-api>=4.1.0
Requires-Dist: httpx[http2]>=0.28.1
